satellite_czml/__init__.py
satellite_czml/czml.py
satellite_czml/satellite_czml.py
satellite_czml-0.1.2.dist-info/LICENSE
satellite_czml-0.1.2.dist-info/LICENSE.txt
satellite_czml-0.1.2.dist-info/METADATA
satellite_czml-0.1.2.dist-info/WHEEL
satellite_czml-0.1.2.dist-info/top_level.txt
satellite_czml-0.1.2.dist-info/RECORD
