Metadata-Version: 2.1
Name: satellite-czml
Version: 0.1.2
Summary: Creates a CZML string based on TLE (Two Line Element set) data for plotting satellites on the open source CesiumJS JavaScript library
Home-page: https://github.com/cassova/satellite-czml
Author: Nicholas Miller
Author-email: miller.nicholas.a@gmail.com
License: MIT
Download-URL: https://github.com/cassova/satellite-czml
Keywords: satellite-czml,satellite,czml,tle,cesium,cesiumjs,tle2czml,sgp4
Platform: UNKNOWN
